{
  "patient_id": "P2192",
  "config": {
    "name": "P2192",
    "age": "45",
    "category": "A",
    "sex": "Male",
    "BMI": "22",
    "height": "173",
    "weight": "66",
    "meal_type": "iv",
    "ards_enabled": "TRUE",
    "ards_severity": "0.9",
    "brain_injury_enabled": "TRUE",
    "brain_injury_severity": "0.3",
    "ventilation": "TRUE",
    "ventilation_mode": "volume control",
    "sub_mode": "assisted control",
    "fio2": "0.6",
    "peep": "10",
    "inspiratory_pressure": "",
    "respiration_rate": "18",
    "flow": "60",
    "tidal_volume": "300"
  },
  "snapshots": [
    {
      "HeartRate": 71.9999999989269,
      "MeanArterialPressure": 95.32341782793958,
      "OxygenSaturation": 0.9741251041946145,
      "ArterialOxygenPressure": 89.01932605743502,
      "ArterialCarbonDioxidePressure": 39.41544604855489,
      "BloodPH": 7.4194972286430785,
      "RespirationRate": 11.999999999999963,
      "TidalVolume": 535.2600906750494,
      "time_hours": 0
    },
    {
      "HeartRate": 134.49239276227166,
      "MeanArterialPressure": 96.85903646170809,
      "OxygenSaturation": 0.9198529471950082,
      "ArterialOxygenPressure": 74.43906964653267,
      "ArterialCarbonDioxidePressure": 73.78377857199945,
      "BloodPH": 7.171077819188785,
      "RespirationRate": 39.99999999999993,
      "TidalVolume": 310.49496812936275,
      "time_hours": 2.0
    },
    {
      "HeartRate": 138.50822283602457,
      "MeanArterialPressure": 96.49787240225156,
      "OxygenSaturation": 0.9190951034686992,
      "ArterialOxygenPressure": 74.3072563150388,
      "ArterialCarbonDioxidePressure": 74.11255251046492,
      "BloodPH": 7.169314130623523,
      "RespirationRate": 39.99999999999993,
      "TidalVolume": 311.0597096124166,
      "time_hours": 4.0
    },
    {
      "HeartRate": 143.3386834539202,
      "MeanArterialPressure": 96.28021405597917,
      "OxygenSaturation": 0.9179116533235129,
      "ArterialOxygenPressure": 73.50449397569594,
      "ArterialCarbonDioxidePressure": 72.87762867586179,
      "BloodPH": 7.175987360234745,
      "RespirationRate": 39.99999999999993,
      "TidalVolume": 331.5112415024644,
      "time_hours": 6.0
    }
  ],
  "error": null,
  "success": true
}