{
  "patient_id": "P2578",
  "config": {
    "name": "P2578",
    "age": "45",
    "category": "A",
    "sex": "Male",
    "BMI": "22",
    "height": "173",
    "weight": "66",
    "meal_type": "iv",
    "ards_enabled": "TRUE",
    "ards_severity": "0.3",
    "brain_injury_enabled": "TRUE",
    "brain_injury_severity": "0.7",
    "ventilation": "TRUE",
    "ventilation_mode": "volume control",
    "sub_mode": "assisted control",
    "fio2": "0.3",
    "peep": "14",
    "inspiratory_pressure": "",
    "respiration_rate": "24",
    "flow": "40",
    "tidal_volume": "500"
  },
  "snapshots": [
    {
      "HeartRate": 71.9999999989269,
      "MeanArterialPressure": 95.32341782793958,
      "OxygenSaturation": 0.9741251041946145,
      "ArterialOxygenPressure": 89.01932605743502,
      "ArterialCarbonDioxidePressure": 39.41544604855489,
      "BloodPH": 7.4194972286430785,
      "RespirationRate": 11.999999999999963,
      "TidalVolume": 535.2600906750494,
      "time_hours": 0
    },
    {
      "HeartRate": 65.9031985150003,
      "MeanArterialPressure": 95.92403543151684,
      "OxygenSaturation": 0.9535727201225818,
      "ArterialOxygenPressure": 71.97834758022263,
      "ArterialCarbonDioxidePressure": 39.264965119208526,
      "BloodPH": 7.421006894684951,
      "RespirationRate": 29.411764705882334,
      "TidalVolume": 449.92483954549203,
      "time_hours": 2.0
    },
    {
      "HeartRate": 69.04942473534656,
      "MeanArterialPressure": 96.06151888792728,
      "OxygenSaturation": 0.9533745475670885,
      "ArterialOxygenPressure": 71.91793491059848,
      "ArterialCarbonDioxidePressure": 39.40123275763755,
      "BloodPH": 7.4196436420126455,
      "RespirationRate": 30.303030303030276,
      "TidalVolume": 436.16208746978253,
      "time_hours": 4.0
    },
    {
      "HeartRate": 73.9639840408365,
      "MeanArterialPressure": 94.45794482913482,
      "OxygenSaturation": 0.9515608130864869,
      "ArterialOxygenPressure": 71.01786322831751,
      "ArterialCarbonDioxidePressure": 39.42432638148637,
      "BloodPH": 7.419412616326696,
      "RespirationRate": 24.000000000000014,
      "TidalVolume": 608.2679080813285,
      "time_hours": 6.0
    }
  ],
  "error": null,
  "success": true
}