{
  "patient_id": "P2814",
  "config": {
    "name": "P2814",
    "age": "45",
    "category": "A",
    "sex": "Male",
    "BMI": "22",
    "height": "173",
    "weight": "66",
    "meal_type": "iv",
    "ards_enabled": "TRUE",
    "ards_severity": "0.3",
    "brain_injury_enabled": "TRUE",
    "brain_injury_severity": "0.7",
    "ventilation": "TRUE",
    "ventilation_mode": "volume control",
    "sub_mode": "assisted control",
    "fio2": "1.0",
    "peep": "10",
    "inspiratory_pressure": "",
    "respiration_rate": "12",
    "flow": "40",
    "tidal_volume": "700"
  },
  "snapshots": [
    {
      "HeartRate": 71.9999999989269,
      "MeanArterialPressure": 95.32341782793958,
      "OxygenSaturation": 0.9741251041946145,
      "ArterialOxygenPressure": 89.01932605743502,
      "ArterialCarbonDioxidePressure": 39.41544604855489,
      "BloodPH": 7.4194972286430785,
      "RespirationRate": 11.999999999999963,
      "TidalVolume": 535.2600906750494,
      "time_hours": 0
    },
    {
      "HeartRate": 57.15585634774643,
      "MeanArterialPressure": 95.63213449464743,
      "OxygenSaturation": 0.9986089441737659,
      "ArterialOxygenPressure": 283.6271724663681,
      "ArterialCarbonDioxidePressure": 44.923630664209064,
      "BloodPH": 7.36777005725284,
      "RespirationRate": 15.95744680851066,
      "TidalVolume": 641.4934030872517,
      "time_hours": 2.0
    },
    {
      "HeartRate": 60.075893685849195,
      "MeanArterialPressure": 95.44801242192192,
      "OxygenSaturation": 0.9984851002363707,
      "ArterialOxygenPressure": 274.9868894049433,
      "ArterialCarbonDioxidePressure": 45.087032982354316,
      "BloodPH": 7.3663324030645745,
      "RespirationRate": 16.042780748663127,
      "TidalVolume": 641.4715851712361,
      "time_hours": 4.0
    },
    {
      "HeartRate": 64.38114728734875,
      "MeanArterialPressure": 95.2022024938383,
      "OxygenSaturation": 0.9978555390344395,
      "ArterialOxygenPressure": 243.3099733157738,
      "ArterialCarbonDioxidePressure": 45.56948846255265,
      "BloodPH": 7.362115201102981,
      "RespirationRate": 16.304347826086985,
      "TidalVolume": 641.4011335033834,
      "time_hours": 6.0
    }
  ],
  "error": null,
  "success": true
}