{
  "patient_id": "P2867",
  "config": {
    "name": "P2867",
    "age": "45",
    "category": "A",
    "sex": "Male",
    "BMI": "22",
    "height": "173",
    "weight": "66",
    "meal_type": "iv",
    "ards_enabled": "TRUE",
    "ards_severity": "0.3",
    "brain_injury_enabled": "TRUE",
    "brain_injury_severity": "0.7",
    "ventilation": "TRUE",
    "ventilation_mode": "volume control",
    "sub_mode": "continuous mandatory ventilation",
    "fio2": "1.0",
    "peep": "14",
    "inspiratory_pressure": "",
    "respiration_rate": "12",
    "flow": "40",
    "tidal_volume": "700"
  },
  "snapshots": [
    {
      "HeartRate": 71.9999999989269,
      "MeanArterialPressure": 95.32341782793958,
      "OxygenSaturation": 0.9741251041946145,
      "ArterialOxygenPressure": 89.01932605743502,
      "ArterialCarbonDioxidePressure": 39.41544604855489,
      "BloodPH": 7.4194972286430785,
      "RespirationRate": 11.999999999999963,
      "TidalVolume": 535.2600906750494,
      "time_hours": 0
    },
    {
      "HeartRate": 59.472512468523014,
      "MeanArterialPressure": 96.11472656743722,
      "OxygenSaturation": 0.998284279862054,
      "ArterialOxygenPressure": 294.6804405431088,
      "ArterialCarbonDioxidePressure": 60.03320615727128,
      "BloodPH": 7.252927405069413,
      "RespirationRate": 10.067114093959656,
      "TidalVolume": 684.4555261198471,
      "time_hours": 2.0
    },
    {
      "HeartRate": 62.5257380812248,
      "MeanArterialPressure": 95.54548858950056,
      "OxygenSaturation": 0.9981518454078576,
      "ArterialOxygenPressure": 286.39725819950127,
      "ArterialCarbonDioxidePressure": 59.991845556417665,
      "BloodPH": 7.253199793832918,
      "RespirationRate": 14.77832512315269,
      "TidalVolume": 668.2044419598135,
      "time_hours": 4.0
    },
    {
      "HeartRate": 70.68673729623858,
      "MeanArterialPressure": 95.47215558097108,
      "OxygenSaturation": 0.9975569768397022,
      "ArterialOxygenPressure": 262.9680409755488,
      "ArterialCarbonDioxidePressure": 62.349229566920506,
      "BloodPH": 7.237913811430079,
      "RespirationRate": 10.452961672473807,
      "TidalVolume": 716.5266512055282,
      "time_hours": 6.0
    }
  ],
  "error": null,
  "success": true
}