{
  "patient_id": "P2880",
  "config": {
    "name": "P2880",
    "age": "45",
    "category": "A",
    "sex": "Male",
    "BMI": "22",
    "height": "173",
    "weight": "66",
    "meal_type": "iv",
    "ards_enabled": "TRUE",
    "ards_severity": "0.3",
    "brain_injury_enabled": "TRUE",
    "brain_injury_severity": "0.7",
    "ventilation": "TRUE",
    "ventilation_mode": "volume control",
    "sub_mode": "assisted control",
    "fio2": "1.0",
    "peep": "14",
    "inspiratory_pressure": "",
    "respiration_rate": "12",
    "flow": "60",
    "tidal_volume": "700"
  },
  "snapshots": [
    {
      "HeartRate": 71.9999999989269,
      "MeanArterialPressure": 95.32341782793958,
      "OxygenSaturation": 0.9741251041946145,
      "ArterialOxygenPressure": 89.01932605743502,
      "ArterialCarbonDioxidePressure": 39.41544604855489,
      "BloodPH": 7.4194972286430785,
      "RespirationRate": 11.999999999999963,
      "TidalVolume": 535.2600906750494,
      "time_hours": 0
    },
    {
      "HeartRate": 57.14473269192344,
      "MeanArterialPressure": 95.62287751737436,
      "OxygenSaturation": 0.9990350529522123,
      "ArterialOxygenPressure": 318.83615924091725,
      "ArterialCarbonDioxidePressure": 42.81976312412611,
      "BloodPH": 7.386742870120031,
      "RespirationRate": 14.423076923076922,
      "TidalVolume": 719.2023826606838,
      "time_hours": 2.0
    },
    {
      "HeartRate": 60.25661178096877,
      "MeanArterialPressure": 95.43692054124358,
      "OxygenSaturation": 0.9989576008478425,
      "ArterialOxygenPressure": 309.8002479080394,
      "ArterialCarbonDioxidePressure": 42.881013938820125,
      "BloodPH": 7.386178389813105,
      "RespirationRate": 14.492753623188404,
      "TidalVolume": 719.186177118039,
      "time_hours": 4.0
    },
    {
      "HeartRate": 64.40512034788534,
      "MeanArterialPressure": 94.8345352789283,
      "OxygenSaturation": 0.9986189189269228,
      "ArterialOxygenPressure": 280.1145505862738,
      "ArterialCarbonDioxidePressure": 43.00489756598463,
      "BloodPH": 7.385037395231845,
      "RespirationRate": 14.563106796116505,
      "TidalVolume": 719.1699847789522,
      "time_hours": 6.0
    }
  ],
  "error": null,
  "success": true
}