{
  "patient_id": "P3277",
  "config": {
    "name": "P3277",
    "age": "45",
    "category": "A",
    "sex": "Male",
    "BMI": "22",
    "height": "173",
    "weight": "66",
    "meal_type": "iv",
    "ards_enabled": "TRUE",
    "ards_severity": "0.6",
    "brain_injury_enabled": "TRUE",
    "brain_injury_severity": "0.7",
    "ventilation": "TRUE",
    "ventilation_mode": "volume control",
    "sub_mode": "continuous mandatory ventilation",
    "fio2": "1.0",
    "peep": "6",
    "inspiratory_pressure": "",
    "respiration_rate": "24",
    "flow": "40",
    "tidal_volume": "300"
  },
  "snapshots": [
    {
      "HeartRate": 71.9999999989269,
      "MeanArterialPressure": 95.32341782793958,
      "OxygenSaturation": 0.9741251041946145,
      "ArterialOxygenPressure": 89.01932605743502,
      "ArterialCarbonDioxidePressure": 39.41544604855489,
      "BloodPH": 7.4194972286430785,
      "RespirationRate": 11.999999999999963,
      "TidalVolume": 535.2600906750494,
      "time_hours": 0
    },
    {
      "HeartRate": 135.23663495621892,
      "MeanArterialPressure": 96.79273978374562,
      "OxygenSaturation": 0.9741444364276027,
      "ArterialOxygenPressure": 135.6316611552965,
      "ArterialCarbonDioxidePressure": 105.5076764137737,
      "BloodPH": 7.028858063589854,
      "RespirationRate": 26.785714285714285,
      "TidalVolume": 309.133314608169,
      "time_hours": 2.0
    },
    {
      "HeartRate": 139.41507412660596,
      "MeanArterialPressure": 96.05986700222675,
      "OxygenSaturation": 0.9728769385077464,
      "ArterialOxygenPressure": 132.3760480183232,
      "ArterialCarbonDioxidePressure": 104.12693127485886,
      "BloodPH": 7.034102861283203,
      "RespirationRate": 27.777777777777768,
      "TidalVolume": 285.09998339326415,
      "time_hours": 4.0
    },
    {
      "HeartRate": 145.82086555099087,
      "MeanArterialPressure": 96.09547839555742,
      "OxygenSaturation": 0.9681906100295264,
      "ArterialOxygenPressure": 126.26049225039623,
      "ArterialCarbonDioxidePressure": 106.40141008162627,
      "BloodPH": 7.025496192527485,
      "RespirationRate": 22.900763358778647,
      "TidalVolume": 291.0321845072259,
      "time_hours": 6.0
    }
  ],
  "error": null,
  "success": true
}