{
  "patient_id": "P3615",
  "config": {
    "name": "P3615",
    "age": "45",
    "category": "A",
    "sex": "Male",
    "BMI": "22",
    "height": "173",
    "weight": "66",
    "meal_type": "iv",
    "ards_enabled": "TRUE",
    "ards_severity": "0.9",
    "brain_injury_enabled": "TRUE",
    "brain_injury_severity": "0.7",
    "ventilation": "TRUE",
    "ventilation_mode": "volume control",
    "sub_mode": "continuous mandatory ventilation",
    "fio2": "0.6",
    "peep": "6",
    "inspiratory_pressure": "",
    "respiration_rate": "24",
    "flow": "60",
    "tidal_volume": "500"
  },
  "snapshots": [
    {
      "HeartRate": 71.9999999989269,
      "MeanArterialPressure": 95.32341782793958,
      "OxygenSaturation": 0.9741251041946145,
      "ArterialOxygenPressure": 89.01932605743502,
      "ArterialCarbonDioxidePressure": 39.41544604855489,
      "BloodPH": 7.4194972286430785,
      "RespirationRate": 11.999999999999963,
      "TidalVolume": 535.2600906750494,
      "time_hours": 0
    },
    {
      "HeartRate": 79.8832098682655,
      "MeanArterialPressure": 95.63138449955808,
      "OxygenSaturation": 0.9080891719550288,
      "ArterialOxygenPressure": 62.43417629169565,
      "ArterialCarbonDioxidePressure": 54.77233090552985,
      "BloodPH": 7.2892818969992375,
      "RespirationRate": 24.00000000000001,
      "TidalVolume": 516.4651340395026,
      "time_hours": 2.0
    },
    {
      "HeartRate": 95.52098628532346,
      "MeanArterialPressure": 96.10561469062968,
      "OxygenSaturation": 0.8997417482085857,
      "ArterialOxygenPressure": 58.97841655730564,
      "ArterialCarbonDioxidePressure": 52.03725386180673,
      "BloodPH": 7.309537419038339,
      "RespirationRate": 26.315789473684227,
      "TidalVolume": 466.00881763929584,
      "time_hours": 4.0
    },
    {
      "HeartRate": 105.08095467908234,
      "MeanArterialPressure": 96.05973859759536,
      "OxygenSaturation": 0.8967934371600711,
      "ArterialOxygenPressure": 57.599867008389836,
      "ArterialCarbonDioxidePressure": 50.20240263748472,
      "BloodPH": 7.323793966269159,
      "RespirationRate": 24.000000000000014,
      "TidalVolume": 577.0208910926307,
      "time_hours": 6.0
    }
  ],
  "error": null,
  "success": true
}